eikosograms/__init__.py
eikosograms/eikosograms.py
eikosograms-0.0.2.dist-info/METADATA
eikosograms-0.0.2.dist-info/WHEEL
eikosograms-0.0.2.dist-info/licenses/LICENSE
eikosograms-0.0.2.dist-info/RECORD
