Metadata-Version: 2.3
Name: eikosograms
Version: 0.0.2
Summary: A small package for drawing eikosograms
Project-URL: Homepage, https://github.com/petro-zdebskyi/eikosograms
Project-URL: Issues, https://github.com/petro-zdebskyi/eikosograms/issues
Author-email: Petro Zdebskyi <petrozd@gmail.com>
Classifier: License :: OSI Approved :: MIT License
Classifier: Operating System :: OS Independent
Classifier: Programming Language :: Python :: 3
Requires-Python: >=3.8
